test.py
python_scap-0.0.6.dist-info/licenses/LICENSE
scap/__init__.py
scap/py.typed
scap/_core/__init__.py
scap/_core/_types.py
scap/_core/http.py
scap/_core/schema.py
scap/_core/sql.py
scap/_core/sql_patch.py
scap/_core/sql_types.py
scap/api/__init__.py
scap/api/cpe.py
scap/schemas/__init__.py
scap/schemas/cpe.py
scap/sql_models/__init__.py
scap/sql_models/cpe.py
scap/tools/__init__.py
scap/tools/cpe.py
python_scap-0.0.6.dist-info/METADATA
python_scap-0.0.6.dist-info/WHEEL
python_scap-0.0.6.dist-info/top_level.txt
python_scap-0.0.6.dist-info/RECORD
